<?xml version="1.0" encoding="UTF-8"?>
<yordamBT>
<yordam hata="0" kayittoplam="541610" kayitbulunan="541597" kayitbaslangic="3" kayitbitis="3" listelenenkayit="1">
<kayit sirano="3">
<ktpKN>A</ktpKN>
<ktp>Beykent Üniversitesi Kütüphanesi</ktp>
<bolumKN>01</bolumKN>
<bolum>Ayazağa</bolum>
<bolumsanalKN/>
<bolumsanal/>
<koleksiyonKN/>
<koleksiyon/>
<turKN>01</turKN>
<tur/>
<altturKN/>
<alttur/>
<sekilKN>01</sekilKN>
<sekil>Basılı</sekil>
<ortamKN>01</ortamKN>
<sekil>Kağıt</sekil>
<sureKN/>
<sure/>
<dilKN>tur</dilKN>
<dil>Türkçe</dil>
<yayintarihi1>2009</yayintarihi1>
<yayintarihi2/>
<siniflama>HB 180.T8/E79 </siniflama>
<demirbas>084401</demirbas>
<cilt/>
<kopya>k.3</kopya>
<eleme/>
<bagis/>
<kurumyayini/>
<bolum>01</bolum>
<oda>Asım Şen Koleksiyonu</oda>
<yazar>Ertek, Tümay</yazar>
<isbnissn>9789752959835</isbnissn>
<eseradi>Temel ekonomi : ( Basından örneklerle)</eseradi>
<sorumlular>Tümay Ertek</sorumlular>
<basimkaydi>gnş. 3. bs.</basimkaydi>
<yayinyeri>İstanbul</yayinyeri>
<yayinlayan>Beta yayınları</yayinlayan>
<fizikseltanim>xvi,605 s. : şkl.; 23 cm.</fizikseltanim>
<sureliayrinti/>
<dizikaydi>Yayın no : 2085, İşletme ekonomi dizisi : 299</dizikaydi>
<notlar>Dipnot var.<br/>
Kaynakça ve dizin var.</notlar>
<tezuniversite/>
<tezenstitu/>
<tezfakulte/>
<tezanabilimdali/>
<tezbilimdali/>
<icindekiler/>
<konubasliklari>Ekonomi.<br/>
Economy.<br/>
Microeconomics.  <br/>
Macroeconomics.  <br/>
</konubasliklari>
<url/>
<kayitURL>http://library.beykent.edu.tr/yordambt/yordam.php?-ac=arama%26demirbas=084401</kayitURL>
<kapakyolu/>
</kayit>
</yordam>
</yordamBT>
